sedexercises/__init__.py
sedexercises/app_guide.md
sedexercises/questions.json
sedexercises/sed_exercises.css
sedexercises/sed_exercises.py
sedexercises/user_progress.json
sedexercises/sample_input/addr.txt
sedexercises/sample_input/anchors.txt
sedexercises/sample_input/blocks.txt
sedexercises/sample_input/broken.txt
sedexercises/sample_input/code.txt
sedexercises/sample_input/copyright.txt
sedexercises/sample_input/f1.txt
sedexercises/sample_input/f2.txt
sedexercises/sample_input/f3.txt
sedexercises/sample_input/f4.txt
sedexercises/sample_input/f5.txt
sedexercises/sample_input/f6.txt
sedexercises/sample_input/fields.txt
sedexercises/sample_input/headers.txt
sedexercises/sample_input/hex.txt
sedexercises/sample_input/nul_separated
sedexercises/sample_input/nums.txt
sedexercises/sample_input/para.txt
sedexercises/sample_input/patterns.txt
sedexercises/sample_input/purchases.txt
sedexercises/sample_input/replace.txt
sedexercises/sample_input/sample.txt
sedexercises/sample_input/text.txt
sedexercises-1.7.0.dist-info/METADATA
sedexercises-1.7.0.dist-info/WHEEL
sedexercises-1.7.0.dist-info/entry_points.txt
sedexercises-1.7.0.dist-info/licenses/LICENSE
sedexercises-1.7.0.dist-info/RECORD
